saqc/__init__.py
saqc/__main__.py
saqc/_version.py
saqc/constants.py
saqc/exceptions.py
saqc/version.py
saqc/core/__init__.py
saqc/core/core.py
saqc/core/flags.py
saqc/core/frame.py
saqc/core/history.py
saqc/core/register.py
saqc/core/translation/__init__.py
saqc/core/translation/basescheme.py
saqc/core/translation/dmpscheme.py
saqc/core/translation/floatscheme.py
saqc/core/translation/positionalscheme.py
saqc/core/translation/simplescheme.py
saqc/funcs/__init__.py
saqc/funcs/breaks.py
saqc/funcs/changepoints.py
saqc/funcs/constants.py
saqc/funcs/curvefit.py
saqc/funcs/drift.py
saqc/funcs/flagtools.py
saqc/funcs/generic.py
saqc/funcs/interpolation.py
saqc/funcs/noise.py
saqc/funcs/outliers.py
saqc/funcs/pattern.py
saqc/funcs/resampling.py
saqc/funcs/residuals.py
saqc/funcs/rolling.py
saqc/funcs/scores.py
saqc/funcs/tools.py
saqc/funcs/transformation.py
saqc/lib/__init__.py
saqc/lib/checking.py
saqc/lib/docs.py
saqc/lib/plotting.py
saqc/lib/rolling.py
saqc/lib/selectionGUI.py
saqc/lib/tools.py
saqc/lib/ts_operators.py
saqc/lib/types.py
saqc/parsing/__init__.py
saqc/parsing/environ.py
saqc/parsing/reader.py
saqc/parsing/visitor.py
saqc-2.7.0.post3.dist-info/licenses/LICENSE.md
saqc-2.7.0.post3.dist-info/licenses/LICENSES/GPL-3.0-or-later.txt
saqc-2.7.0.post3.dist-info/METADATA
saqc-2.7.0.post3.dist-info/WHEEL
saqc-2.7.0.post3.dist-info/entry_points.txt
saqc-2.7.0.post3.dist-info/top_level.txt
saqc-2.7.0.post3.dist-info/RECORD
