Metadata-Version: 2.4
Name: saqc
Version: 2.7.0.post3
Summary: A timeseries data quality control and processing tool/framework
Home-page: https://git.ufz.de/rdm-software/saqc
Author: David Schaefer, Bert Palm, Peter Luenenschloss
Author-email: david.schaefer@ufz.de
Requires-Python: >=3.10
License-File: LICENSE.md
License-File: LICENSES/GPL-3.0-or-later.txt
Requires-Dist: Click
Requires-Dist: docstring_parser
Requires-Dist: fancy-collections
Requires-Dist: fastdtw
Requires-Dist: matplotlib
Requires-Dist: numpy
Requires-Dist: outlier-utils
Requires-Dist: pyarrow
Requires-Dist: pandas
Requires-Dist: pydantic
Requires-Dist: scikit-learn
Requires-Dist: scipy
Requires-Dist: typing_extensions
Provides-Extra: fm
Requires-Dist: momentfm; extra == "fm"
Dynamic: author
Dynamic: author-email
Dynamic: description
Dynamic: description-content-type
Dynamic: home-page
Dynamic: license-file
Dynamic: provides-extra
Dynamic: requires-dist
Dynamic: requires-python
Dynamic: summary
